promptoor/__init__.py
promptoor/cli.py
promptoor-0.1.0.dist-info/METADATA
promptoor-0.1.0.dist-info/WHEEL
promptoor-0.1.0.dist-info/entry_points.txt
promptoor-0.1.0.dist-info/top_level.txt
promptoor-0.1.0.dist-info/RECORD
