Metadata-Version: 2.4
Name: promptoor
Version: 0.1.0
Summary: Package your repo for pasting into an LLM prompt, respecting .gitignore., completely generated by chatgpt
Author-email: Jitender Shekhawat <me@jitendershekhawat.com>
Requires-Python: >=3.7
Requires-Dist: pathspec>=0.11.1
